Metadata-Version: 2.4
Name: llama-index-kvstore-couchbase
Version: 0.3.1
Summary: llama-index kvstore couchbase integration
Author-email: Couchbase <devadvocates@couchbase.com>
License-Expression: MIT
License-File: LICENSE
Requires-Python: <4.0,>=3.9
Requires-Dist: couchbase<5,>=4.3.0
Requires-Dist: llama-index-core<0.15,>=0.13.0
